dreamsound/__init__.py
dreamsound/downloader.py
dreamsound/dreamsound.py
dreamsound-0.1.6.3.dist-info/LICENSE
dreamsound-0.1.6.3.dist-info/METADATA
dreamsound-0.1.6.3.dist-info/WHEEL
dreamsound-0.1.6.3.dist-info/top_level.txt
dreamsound-0.1.6.3.dist-info/RECORD
