Metadata-Version: 2.1
Name: dreamsound
Version: 0.1.6.3
Summary: DreamSound Class for CNN Activation Layer Sonification
Home-page: https://github.com/fdch/dreamsound
Author: Fede Camara Halac
Author-email: fch226@nyu.edu
License: UNKNOWN
Project-URL: Bug Tracker, https://github.com/fdch/dreamsound/issues
Keywords: deep learning,sound,yamnet
Platform: UNKNOWN
Classifier: Topic :: Multimedia :: Sound/Audio :: Sound Synthesis
Classifier: Programming Language :: Python :: 3
Classifier: License :: OSI Approved :: GNU General Public License (GPL)
Classifier: Operating System :: OS Independent
Requires-Python: >=3.6
License-File: LICENSE
Requires-Dist: requests
Requires-Dist: numpy
Requires-Dist: matplotlib
Requires-Dist: librosa
Requires-Dist: tensorflow
